zzz/pyearthtools/__init__.py
zzz/pyearthtools/_core_classes.py
pyearthtools-0.5.1.dist-info/METADATA
pyearthtools-0.5.1.dist-info/WHEEL
pyearthtools-0.5.1.dist-info/licenses/LICENSE
pyearthtools-0.5.1.dist-info/licenses/NOTICE.md
pyearthtools-0.5.1.dist-info/RECORD
