Metadata-Version: 2.4
Name: pyearthtools
Version: 0.5.1
Summary: PyEarthTools: Machine learning for Earth system science.
Project-URL: homepage, https://pyearthtools.readthedocs.io/
Project-URL: documentation, https://pyearthtools.readthedocs.io/
Project-URL: repository, https://github.com/ACCESS-Community-Hub/PyEarthTools
Maintainer-email: Tennessee Leeuwenburg <tennessee.leeuwenburg@bom.gov.au>
License-File: LICENSE
License-File: NOTICE.md
Keywords: pyearthtools
Classifier: License :: OSI Approved :: Apache Software License
Classifier: Operating System :: OS Independent
Classifier: Programming Language :: Python :: 3
Requires-Python: >=3.11
Requires-Dist: pyearthtools-data[all]>=0.5.1
Requires-Dist: pyearthtools-pipeline[all]>=0.5.1
Requires-Dist: pyearthtools-training[all]>=0.5.1
Requires-Dist: pyearthtools-utils>=0.5.1
Requires-Dist: pyearthtools-zoo>=0.5.1
Provides-Extra: all
Requires-Dist: pyearthtools-data[all]>=0.5.1; extra == 'all'
Requires-Dist: pyearthtools-pipeline[all]>=0.5.1; extra == 'all'
Requires-Dist: pyearthtools-training[all]>=0.5.1; extra == 'all'
Requires-Dist: pyearthtools-utils>=0.5.1; extra == 'all'
Requires-Dist: pyearthtools-zoo>=0.5.1; extra == 'all'
Provides-Extra: data
Requires-Dist: pyearthtools-data>=0.5.1; extra == 'data'
Provides-Extra: dev
Requires-Dist: black==25.1.0; extra == 'dev'
Requires-Dist: interrogate; extra == 'dev'
Requires-Dist: pre-commit; extra == 'dev'
Requires-Dist: ruff; extra == 'dev'
Provides-Extra: docs
Requires-Dist: bottleneck; extra == 'docs'
Requires-Dist: myst-parser; extra == 'docs'
Requires-Dist: nbsphinx; extra == 'docs'
Requires-Dist: pandas; extra == 'docs'
Requires-Dist: scipy; extra == 'docs'
Requires-Dist: scores; extra == 'docs'
Requires-Dist: sphinx; extra == 'docs'
Requires-Dist: sphinx-book-theme; extra == 'docs'
Requires-Dist: sphinx-design; extra == 'docs'
Requires-Dist: sphinx-gallery; extra == 'docs'
Requires-Dist: sphinx-togglebutton; extra == 'docs'
Requires-Dist: sphinxcontrib-mermaid; extra == 'docs'
Requires-Dist: xarray; extra == 'docs'
Provides-Extra: pipeline
Requires-Dist: pyearthtools-data>=0.5.1; extra == 'pipeline'
Requires-Dist: pyearthtools-pipeline>=0.5.1; extra == 'pipeline'
Requires-Dist: pyearthtools-utils>=0.5.1; extra == 'pipeline'
Provides-Extra: test
Requires-Dist: pudb; extra == 'test'
Requires-Dist: pytest; extra == 'test'
Requires-Dist: pytest-cov; extra == 'test'
Requires-Dist: pytest-xdist; extra == 'test'
Provides-Extra: training
Requires-Dist: pyearthtools-data>=0.5.1; extra == 'training'
Requires-Dist: pyearthtools-pipeline>=0.5.1; extra == 'training'
Requires-Dist: pyearthtools-training>=0.5.1; extra == 'training'
Requires-Dist: pyearthtools-utils>=0.5.1; extra == 'training'
Provides-Extra: utils
Requires-Dist: pyearthtools-utils>=0.5.1; extra == 'utils'
Provides-Extra: zoo
Requires-Dist: pyearthtools-data>=0.5.1; extra == 'zoo'
Requires-Dist: pyearthtools-pipeline>=0.5.1; extra == 'zoo'
Requires-Dist: pyearthtools-training>=0.5.1; extra == 'zoo'
Requires-Dist: pyearthtools-utils>=0.5.1; extra == 'zoo'
Requires-Dist: pyearthtools-zoo>=0.5.1; extra == 'zoo'
